golgotha.py
golgotha-1.0.1.dist-info/METADATA
golgotha-1.0.1.dist-info/WHEEL
golgotha-1.0.1.dist-info/entry_points.txt
golgotha-1.0.1.dist-info/license.txt
golgotha-1.0.1.dist-info/top_level.txt
golgotha-1.0.1.dist-info/RECORD
