Metadata-Version: 2.1
Name: golgotha
Version: 1.0.1
Summary: A preprocessor to define new operators in any programming language.
Author: Wyatt S Carpenter
Maintainer: Wyatt S Carpenter
Project-URL: Homepage, https://github.com/wyattscarpenter/golgotha
Project-URL: Documentation, https://github.com/wyattscarpenter/golgotha/blob/master/readme.txt
Project-URL: Repository, https://github.com/wyattscarpenter/golgotha.git
Project-URL: Issues, https://github.com/wyattscarpenter/golgotha/issues
Keywords: preprocessor,operators,infix,prefix,postfix,syntax,💀,🔣
Classifier: Development Status :: 5 - Production/Stable
Classifier: Environment :: Console
Classifier: Intended Audience :: Developers
Classifier: License :: CC0 1.0 Universal (CC0 1.0) Public Domain Dedication
Classifier: License :: OSI Approved :: MIT No Attribution License (MIT-0)
Classifier: Programming Language :: Python :: 3
Classifier: Topic :: Software Development :: Build Tools
Classifier: Topic :: Software Development :: Code Generators
Classifier: Topic :: Software Development :: Pre-processors
Requires-Python: >=3
License-File: license.txt
Requires-Dist: regex
Provides-Extra: dev
Requires-Dist: types-regex ; extra == 'dev'
Requires-Dist: ruff ; extra == 'dev'
Requires-Dist: mypy ; extra == 'dev'
Requires-Dist: pyright ; extra == 'dev'
